setup.cfg
setup.py
windhelper/__init__.py
windhelper/first_model.py
windhelper/mapper.py
windhelper/wind_helper_test.py
windhelper/windhelper.py
windhelper.egg-info/PKG-INFO
windhelper.egg-info/SOURCES.txt
windhelper.egg-info/dependency_links.txt
windhelper.egg-info/top_level.txt
windhelper.egg-info/zip-safe