Metadata-Version: 1.0
Name: windhelper
Version: 0.2.3
Summary: encapsulate the windPy API with pandas
Home-page: https://github.com/wangluzhou/windHelper.git
Author: wangluzhou
Author-email: wangluzhou@aliyun.com
License: MIT
Platform: UNKNOWN
